exputils/__init__.py
exputils/data/__init__.py
exputils/data/loading.py
exputils/data/logger.py
exputils/data/logging.py
exputils/data/selection.py
exputils/data/statistics.py
exputils/data/utils.py
exputils/gui/__init__.py
exputils/gui/misc.py
exputils/gui/jupyter/__init__.py
exputils/gui/jupyter/base_widget.py
exputils/gui/jupyter/code_producer_widget.py
exputils/gui/jupyter/experiment_data_loader_widget.py
exputils/gui/jupyter/experiment_data_plot_selection_widget.py
exputils/gui/jupyter/experiment_data_selection_widget.py
exputils/gui/jupyter/experiment_ids_selection_widget.py
exputils/gui/jupyter/misc.py
exputils/gui/jupyter/multi_selection_widget.py
exputils/gui/jupyter/plotly_box.py
exputils/gui/jupyter/plotly_meanstd_bar.py
exputils/gui/jupyter/plotly_meanstd_scatter.py
exputils/gui/jupyter/repetition_ids_selection_widget.py
exputils/gui/jupyter/tabulate_meanstd.py
exputils/gui/jupyter/tabulate_pairwise.py
exputils/gui/jupyter/text_selection_accordion_widget.py
exputils/io/__init__.py
exputils/io/dill.py
exputils/io/general.py
exputils/io/json.py
exputils/io/numpy.py
exputils/io/odsreader.py
exputils/manage/__init__.py
exputils/manage/experimentgenerator.py
exputils/manage/experimentstarter.py
exputils/manage/misc.py
exputils/misc/__init__.py
exputils/misc/attrdict.py
exputils/misc/misc.py
experiment_utilities-0.3.9.dist-info/LICENSE
experiment_utilities-0.3.9.dist-info/METADATA
experiment_utilities-0.3.9.dist-info/WHEEL
experiment_utilities-0.3.9.dist-info/top_level.txt
experiment_utilities-0.3.9.dist-info/RECORD
