Metadata-Version: 2.2
Name: experiment-utilities
Version: 0.3.9
Summary: Management of scientific experiments including their configuration, logging of data, execution and visualization of results.
Author-email: Chris Reinke <c.reinke85@gmail.com>
License: GNU GENERAL PUBLIC LICENSE
Project-URL: Homepage, https://github.com/ChrisReinke/exputils
Project-URL: Documentation, https://chrisreinke.github.io/exputils
Project-URL: Repository, https://github.com/ChrisReinke/exputils.git
Project-URL: Issues, https://github.com/ChrisReinke/exputils/issues
Keywords: automation,research,tool
Classifier: Development Status :: 4 - Beta
Classifier: Programming Language :: Python
Classifier: Intended Audience :: Science/Research
Classifier: License :: OSI Approved :: GNU General Public License v3 or later (GPLv3+)
Classifier: Topic :: Scientific/Engineering
Classifier: Topic :: Software Development :: Libraries :: Python Modules
Classifier: Topic :: Utilities
Requires-Python: >=3.8
License-File: LICENSE
Requires-Dist: numpy>=1.19.5
Requires-Dist: six>=1.15.0
Requires-Dist: notebook<=6.5.6
Requires-Dist: ipywidgets<=7.6.5,>=7.5.1
Requires-Dist: jupyter_contrib_nbextensions>=0.7.0
Requires-Dist: qgrid>=1.3.1
Requires-Dist: ipynbname>=2023.2.0.0
Requires-Dist: plotly>=4.13.0
Requires-Dist: cloudpickle>=1.6.0
Requires-Dist: dill>=0.3.3
Requires-Dist: odfpy>=1.4.1
Requires-Dist: tabulate>=0.8.9
Requires-Dist: scipy>=1.5.4
Requires-Dist: tensorboard>=1.15.0
Requires-Dist: fasteners>=0.18
Requires-Dist: pyyaml>=6.0
Provides-Extra: test
Requires-Dist: pytest; extra == "test"
Requires-Dist: torch; extra == "test"
Provides-Extra: docs
Requires-Dist: mkdocs; extra == "docs"
Requires-Dist: mkdocstrings-python; extra == "docs"
Requires-Dist: mkdocs-material; extra == "docs"
